signal_analyzer/__init__.py
signal_analyzer/analysis/__init__.py
signal_analyzer/analysis/clusters.py
signal_analyzer/analysis/feasibility.py
signal_analyzer/analysis/frontiers.py
signal_analyzer/analysis/geometry.py
signal_analyzer/analysis/ordering.py
signal_analyzer/analysis/volnorm.py
signal_analyzer/analyzer.py
signal_analyzer/core/__init__.py
signal_analyzer/core/events.py
signal_analyzer/core/trades.py
signal_analyzer/core/utils.py
signal_analyzer/plotting/__init__.py
signal_analyzer/plotting/clusters.py
signal_analyzer/plotting/frontiers.py
signal_analyzer/plotting/heatmaps.py
signal_analyzer/plotting/scatter.py
signal_analyzer/plotting/volnorm.py
signal_analyzer/report/__init__.py
signal_analyzer/report/summaries.py
trade_geometry_analyzer-0.1.0.dist-info/METADATA
trade_geometry_analyzer-0.1.0.dist-info/WHEEL
trade_geometry_analyzer-0.1.0.dist-info/RECORD
