Metadata-Version: 2.1
Name: trade-geometry-analyzer
Version: 0.1.0
Summary: Trade geometry diagnostic engine for analyzing post-entry behavior of trading signals
Author: ali askar
Author-email: 26202651+alihaskar@users.noreply.github.com
Requires-Python: >=3.12,<4.0
Classifier: Programming Language :: Python :: 3
Classifier: Programming Language :: Python :: 3.12
Requires-Dist: matplotlib (>=3.10.0,<4.0.0)
Requires-Dist: numpy (>=2.2.3,<3.0.0)
Requires-Dist: pandas (>=2.2.3,<3.0.0)
Requires-Dist: scikit-learn (>=1.6.1,<2.0.0)
Requires-Dist: scipy (>=1.15.1,<2.0.0)
